LICENSE
MANIFEST.in
README.md
requirements.txt
setup.py
Blacksheep_RateLimiter.egg-info/PKG-INFO
Blacksheep_RateLimiter.egg-info/SOURCES.txt
Blacksheep_RateLimiter.egg-info/dependency_links.txt
Blacksheep_RateLimiter.egg-info/requires.txt
Blacksheep_RateLimiter.egg-info/top_level.txt
blacksheep_ratelimiter/__init__.py
blacksheep_ratelimiter/core.py
blacksheep_ratelimiter/utils.py