Metadata-Version: 2.1
Name: Blacksheep-RateLimiter
Version: 1.0.6
Summary: RateLimit Middleware for Blacksheep
Home-page: https://github.com/concordchat/Blacksheep-RateLimiter
Author: Concord
License: MIT
Platform: UNKNOWN
Requires-Python: >=3.9
License-File: LICENSE
